stdcomQt/__init__.py
stdcomQt/pjanicesimple.py
stdcomQt/pjanicesimple.ui
stdcomQt/stdcomQt.py
stdcomQt/stdcomQtC20.py
stdcomQt/stdcomQtPjanice.py
stdcomQt/stdcomQtargs.py
stdcomQt/stdcomipconfigdialog.py
stdcomQt/stdcomipconfigdialog.ui
stdcomQt/stdcompostgresconfig.py
stdcomQt/stdcomsqlconfig.py
stdcomQt/stdcomsqlconfig.ui
stdcomQt/stdcomutilitywidgets.py
stdcomQt/stdcomvsettings.py
stdcomQt/stdpostgresdialog.py
stdcomQt/stdvremsoftsql.py
stdcomQt/stedcompostgresconfig.py
stdcomQt/stedcompostgresconfig.ui
stdcomQt/__pycache__/__init__.cpython-310.pyc
stdcomQt/__pycache__/pjanicesimple.cpython-310.pyc
stdcomQt/__pycache__/stdcomQt.cpython-310.pyc
stdcomQt/__pycache__/stdcomQtC20.cpython-310.pyc
stdcomQt/__pycache__/stdcomQtPjanice.cpython-310.pyc
stdcomQt/__pycache__/stdcomQtargs.cpython-310.pyc
stdcomQt/__pycache__/stdcomipconfigdialog.cpython-310.pyc
stdcomQt/__pycache__/stdcompostgresconfig.cpython-310.pyc
stdcomQt/__pycache__/stdcomsqlconfig.cpython-310.pyc
stdcomQt/__pycache__/stdcomutilitywidgets.cpython-310.pyc
stdcomQt/__pycache__/stdcomvsettings.cpython-310.pyc
stdcomQt/__pycache__/stdvremsoftsql.cpython-310.pyc
stdcomQt/__pycache__/stedcompostgresconfig.cpython-310.pyc
stdcomQt/examples/Stec.PJanice
stdcomQt/examples/multipleSubs.py
stdcomQt/examples/pjaniceExample.py
stdcomQt/utilitys/Stec.PJanice
stdcomQt/utilitys/pjaniceExt.py
stdcomQt/utilitys/sqlplayback.py
stdcomQt/utilitys/sqlplayback.ui
stdcomQt/utilitys/stdautomap.py
stdcomQt/utilitys/stdautomap.ui
stdcomQt/utilitys/stdautomap2.py
stdcomQt/utilitys/stdautomap2.ui
stdcomQt/utilitys/stdcomAutomap.py
stdcomQt/utilitys/stdcomAutomap2.py
stdcomQt/utilitys/stdcomplot.py
stdcomQt/utilitys/stdcomsqlplayback.py
stdcomQt/utilitys/__pycache__/pjaniceExt.cpython-310.pyc
stdcomQt/utilitys/__pycache__/sqlplayback.cpython-310.pyc
stdcomQt/utilitys/__pycache__/stdautomap.cpython-310.pyc
stdcomQt/utilitys/__pycache__/stdautomap2.cpython-310.pyc
stdcomQt/utilitys/__pycache__/stdcomplot.cpython-310.pyc
stdcomQt-1.4.3.dist-info/LICENSE.txt
stdcomQt-1.4.3.dist-info/METADATA
stdcomQt-1.4.3.dist-info/WHEEL
stdcomQt-1.4.3.dist-info/top_level.txt
stdcomQt-1.4.3.dist-info/RECORD
